lopata_bot_proto/__init__.py
lopata_bot_proto/client_pb2.py
lopata_bot_proto/client_pb2.pyi
lopata_bot_proto/client_pb2_grpc.py
lopata_bot_proto/py.typed
lopata_bot_proto-1.0.0.dist-info/METADATA
lopata_bot_proto-1.0.0.dist-info/WHEEL
lopata_bot_proto-1.0.0.dist-info/top_level.txt
lopata_bot_proto-1.0.0.dist-info/RECORD
