Metadata-Version: 2.1
Name: lopata-bot-proto
Version: 1.0.0
Summary: GRPC client for lopata_bot_proto
Author: ci
Author-email: p.a.anokhin@gmail.com
